LICENSE
simple_django_htmx/.gitignore
simple_django_htmx/__init__.py
simple_django_htmx/apps.py
simple_django_htmx/hx_requests.py
simple_django_htmx/templates/simple_django_htmx/messages.html
simple_django_htmx/templatetags/__init__.py
simple_django_htmx/templatetags/hx_tags.py
simple_django_htmx/utils.py
simple_django_htmx/views.py
simple_django_htmx-1.0.1.dist-info/LICENSE
simple_django_htmx-1.0.1.dist-info/WHEEL
simple_django_htmx-1.0.1.dist-info/METADATA
simple_django_htmx-1.0.1.dist-info/RECORD
