Metadata-Version: 2.1
Name: simple-django-htmx
Version: 1.0.1
Summary: Simple package that facilitates the usage of HTMX with Django
Home-page: https://github.com/yaakovLowenstein/simple-django-htmx
License: MIT
Keywords: django,htmx
Author: yaakovLowenstein
Author-email: lowensteinyaakov@gmail.com
Requires-Python: >=3.8,<4.0
Classifier: Environment :: Web Environment
Classifier: Framework :: Django
Classifier: Framework :: Django :: 3.2
Classifier: Framework :: Django :: 4.0
Classifier: Framework :: Django :: 4.1
Classifier: Intended Audience :: Developers
Classifier: License :: OSI Approved :: MIT License
Classifier: Operating System :: OS Independent
Classifier: Programming Language :: Python
Classifier: Programming Language :: Python :: 3
Classifier: Programming Language :: Python :: 3.10
Classifier: Programming Language :: Python :: 3.8
Classifier: Programming Language :: Python :: 3.9
Requires-Dist: Django (>=3.2)
Project-URL: Repository, https://github.com/yaakovLowenstein/simple-django-htmx
